vr/__init__.py
vr/launch/__init__.py
vr/launch/cmdline.py
vr/launch/config.py
vr.launch-2.0.0.dist-info/LICENSE
vr.launch-2.0.0.dist-info/METADATA
vr.launch-2.0.0.dist-info/WHEEL
vr.launch-2.0.0.dist-info/top_level.txt
vr.launch-2.0.0.dist-info/RECORD
