Metadata-Version: 2.1
Name: vr.launch
Version: 2.0.0
Summary: Facilities for launching apps under Velociraptor
Home-page: https://github.com/yougov/vr.launch
Author: YouGov, Plc.
Author-email: open-source@yougov.com
License: UNKNOWN
Platform: UNKNOWN
Classifier: Development Status :: 5 - Production/Stable
Classifier: Intended Audience :: Developers
Classifier: License :: OSI Approved :: MIT License
Classifier: Programming Language :: Python :: 2.7
Classifier: Programming Language :: Python :: 3
Requires-Python: >=2.7
Requires-Dist: pyyaml
Requires-Dist: yamlenv
Requires-Dist: jaraco.collections (!=1.2)
Requires-Dist: six
Provides-Extra: docs
Requires-Dist: sphinx ; extra == 'docs'
Requires-Dist: jaraco.packaging (>=3.2) ; extra == 'docs'
Requires-Dist: rst.linker (>=1.9) ; extra == 'docs'
Provides-Extra: testing
Requires-Dist: pytest (!=3.7.3,>=3.5) ; extra == 'testing'
Requires-Dist: pytest-checkdocs ; extra == 'testing'
Requires-Dist: pytest-flake8 ; extra == 'testing'
